napari_affinities/__init__.py
napari_affinities/_reader.py
napari_affinities/_version.py
napari_affinities/_writer.py
napari_affinities/napari.yaml
napari_affinities/sample_data.py
napari_affinities/_tests/__init__.py
napari_affinities/_tests/conftest.py
napari_affinities/_tests/test_samples.py
napari_affinities/_tests/test_widget.py
napari_affinities/bioimageio/__init__.py
napari_affinities/bioimageio/helpers.py
napari_affinities/gp/__init__.py
napari_affinities/gp/pipeline.py
napari_affinities/gp/nodes/__init__.py
napari_affinities/gp/nodes/binarize.py
napari_affinities/gp/nodes/napari_image_source.py
napari_affinities/gp/nodes/napari_label_source.py
napari_affinities/gp/nodes/np_source.py
napari_affinities/gp/nodes/ones_source.py
napari_affinities/sample_data/lightsheet_nuclei_test_data
napari_affinities/sample_data/per01_100.zarr/.zgroup
napari_affinities/sample_data/per01_100.zarr/volumes/.zgroup
napari_affinities/sample_data/per01_100.zarr/volumes/gt_affs/.zarray
napari_affinities/sample_data/per01_100.zarr/volumes/gt_affs/0.0.0
napari_affinities/sample_data/per01_100.zarr/volumes/gt_labels/.zarray
napari_affinities/sample_data/per01_100.zarr/volumes/gt_labels/0.0.0
napari_affinities/sample_data/per01_100.zarr/volumes/raw/.zarray
napari_affinities/sample_data/per01_100.zarr/volumes/raw/0.0.0
napari_affinities/sample_data/per01_100.zarr/volumes/raw/0.1.0
napari_affinities/widgets/__init__.py
napari_affinities/widgets/affinities.py
napari_affinities/widgets/fov.py
napari_affinities/widgets/gui_helpers.py
napari_affinities/widgets/mutex_watershed.py
napari_affinities-0.1.3.dist-info/LICENSE
napari_affinities-0.1.3.dist-info/METADATA
napari_affinities-0.1.3.dist-info/WHEEL
napari_affinities-0.1.3.dist-info/entry_points.txt
napari_affinities-0.1.3.dist-info/top_level.txt
napari_affinities-0.1.3.dist-info/RECORD
